nickyspatial/__init__.py
nickyspatial/core/__init__.py
nickyspatial/core/classifier.py
nickyspatial/core/layer.py
nickyspatial/core/rules.py
nickyspatial/core/segmentation.py
nickyspatial/filters/__init__.py
nickyspatial/filters/spatial.py
nickyspatial/filters/spectral.py
nickyspatial/io/__init__.py
nickyspatial/io/raster.py
nickyspatial/io/vector.py
nickyspatial/stats/__init__.py
nickyspatial/stats/basic.py
nickyspatial/stats/spatial.py
nickyspatial/stats/spectral.py
nickyspatial/utils/__init__.py
nickyspatial/utils/helpers.py
nickyspatial/viz/__init__.py
nickyspatial/viz/charts.py
nickyspatial/viz/maps.py
nickyspatial-1.1.1.dist-info/METADATA
nickyspatial-1.1.1.dist-info/WHEEL
nickyspatial-1.1.1.dist-info/licenses/LICENSE
nickyspatial-1.1.1.dist-info/RECORD
