Metadata-Version: 2.4
Name: nickyspatial
Version: 1.1.1
Summary: An open-source object-based image analysis library for remote sensing.
Project-URL: documentation, https://kshitijrajsharma.github.io/nickyspatial
Project-URL: repository, https://github.com/kshitijrajsharma/nickyspatial
Author-email: Kshitij Raj Sharma <krschap@duck.com>
License: MIT
License-File: LICENSE
Keywords: obia,object,remote-sensing,segmentation
Classifier: Intended Audience :: Developers
Classifier: License :: OSI Approved :: MIT License
Classifier: Natural Language :: English
Classifier: Programming Language :: Python :: 3.10
Classifier: Programming Language :: Python :: 3.11
Classifier: Programming Language :: Python :: 3.12
Classifier: Topic :: Scientific/Engineering :: GIS
Requires-Python: >=3.10
Requires-Dist: folium>=0.19.5
Requires-Dist: geopandas>=1.0.1
Requires-Dist: ipympl>=0.9.7
Requires-Dist: ipywidgets>=8.1.7
Requires-Dist: matplotlib>=3.10.1
Requires-Dist: nbformat>=5.10.4
Requires-Dist: numexpr>=2.10.2
Requires-Dist: pandas>=2.2.3
Requires-Dist: plotly>=6.0.1
Requires-Dist: rasterio>=1.4.3
Requires-Dist: scikit-image>=0.25.2
Requires-Dist: scikit-learn>=1.6.1
Requires-Dist: scipy>=1.15.2
Requires-Dist: seaborn>=0.13.2
Requires-Dist: streamlit-folium>=0.24.1
Provides-Extra: docs
Requires-Dist: mdx-truly-sane-lists>=1.3; extra == 'docs'
Requires-Dist: mkdocs-git-revision-date-localized-plugin>=1.4.5; extra == 'docs'
Requires-Dist: mkdocs-jupyter>=0.25.1; extra == 'docs'
Requires-Dist: mkdocs-material>=9.6.11; extra == 'docs'
Requires-Dist: mkdocs>=1.6.1; extra == 'docs'
Requires-Dist: mkdocstrings-python>=1.16.10; extra == 'docs'
